wtforms_ext/__init__.py
wtforms_ext/fields.py
wtforms_ext/utils.py
wtforms_ext/validators.py
wtforms_ext/widgets.py
WTForms_Ext-0.5.dist-info/LICENSE
WTForms_Ext-0.5.dist-info/METADATA
WTForms_Ext-0.5.dist-info/WHEEL
WTForms_Ext-0.5.dist-info/top_level.txt
WTForms_Ext-0.5.dist-info/RECORD
